msetoolbox/__init__.py
msetoolbox-0.0.1.dist-info/LICENSE
msetoolbox-0.0.1.dist-info/METADATA
msetoolbox-0.0.1.dist-info/WHEEL
msetoolbox-0.0.1.dist-info/top_level.txt
msetoolbox-0.0.1.dist-info/RECORD
