Metadata-Version: 2.1
Name: msetoolbox
Version: 0.0.1
Summary: MSE Toolbox
Home-page: https://github.com/IntegralEnvision/MSE_Toolbox.git
Author: Integral-Corp
Author-email: Ashley Ellenson <aellenson@integral-corp.com>
License: MIT
Project-URL: Homepage, https://github.com/IntegralEnvision/MSE_Toolbox.git
Classifier: Programming Language :: Python
Classifier: License :: OSI Approved :: MIT License
Classifier: Operating System :: OS Independent
Requires-Python: >=3.0
License-File: LICENSE
